bookmarks_curses/__init__.py
bookmarks_curses/__main__.py
bookmarks_curses/db.py
bookmarks_curses/import_diigo.py
bookmarks_curses/utils.py
bookmarks_curses/curses_utils/__init__.py
bookmarks_curses/curses_utils/list1.py
bookmarks_curses/curses_utils/list2.py
bookmarks_curses/curses_utils/list3.py
bookmarks_curses-0.8.2.dist-info/METADATA
bookmarks_curses-0.8.2.dist-info/WHEEL
bookmarks_curses-0.8.2.dist-info/entry_points.txt
bookmarks_curses-0.8.2.dist-info/licenses/LICENSE.txt
bookmarks_curses-0.8.2.dist-info/RECORD
