Metadata-Version: 2.4
Name: bookmarks-curses
Version: 0.8.2
Summary: A bookmark manager as a curses frontend to sqlite database
Project-URL: homepage, https://github.com/shamilbi/bookmarks-curses
Author-email: Shamil Bikineyev <shamilbi@gmail.com>
License-Expression: GPL-2.0+
License-File: LICENSE.txt
Keywords: bookmark manager
Classifier: Development Status :: 4 - Beta
Classifier: Environment :: Console
Classifier: Natural Language :: English
Classifier: Operating System :: POSIX :: Linux
Classifier: Programming Language :: Python
Classifier: Programming Language :: Python :: 3
Classifier: Programming Language :: Python :: 3 :: Only
Classifier: Programming Language :: Python :: 3.9
Classifier: Programming Language :: Python :: 3.10
Classifier: Programming Language :: Python :: 3.11
Classifier: Programming Language :: Python :: 3.12
Classifier: Programming Language :: Python :: 3.13
Classifier: Programming Language :: Python :: Implementation :: CPython
Requires-Python: >=3.10
